README.md
setup.py
bin/ponctl
ponstar/__init__.py
ponstar/annotations_pb2.py
ponstar/annotations_pb2_grpc.py
ponstar/device_info.py
ponstar/http_pb2.py
ponstar/http_pb2_grpc.py
ponstar/ind.py
ponstar/openolt_pb2.py
ponstar/openolt_pb2_grpc.py
ponstar.egg-info/PKG-INFO
ponstar.egg-info/SOURCES.txt
ponstar.egg-info/dependency_links.txt
ponstar.egg-info/requires.txt
ponstar.egg-info/top_level.txt